odoo/addons/excel_import_export/README.rst
odoo/addons/excel_import_export/__init__.py
odoo/addons/excel_import_export/__manifest__.py
odoo/addons/excel_import_export/controllers/__init__.py
odoo/addons/excel_import_export/controllers/report.py
odoo/addons/excel_import_export/i18n/es.po
odoo/addons/excel_import_export/i18n/excel_import_export.pot
odoo/addons/excel_import_export/i18n/it.po
odoo/addons/excel_import_export/i18n/zh_CN.po
odoo/addons/excel_import_export/models/__init__.py
odoo/addons/excel_import_export/models/common.py
odoo/addons/excel_import_export/models/ir_report.py
odoo/addons/excel_import_export/models/styles.py
odoo/addons/excel_import_export/models/xlsx_export.py
odoo/addons/excel_import_export/models/xlsx_import.py
odoo/addons/excel_import_export/models/xlsx_report.py
odoo/addons/excel_import_export/models/xlsx_template.py
odoo/addons/excel_import_export/readme/CONFIGURE.md
odoo/addons/excel_import_export/readme/CONTRIBUTORS.md
odoo/addons/excel_import_export/readme/DESCRIPTION.md
odoo/addons/excel_import_export/readme/INSTALL.md
odoo/addons/excel_import_export/readme/ROADMAP.md
odoo/addons/excel_import_export/readme/USAGE.md
odoo/addons/excel_import_export/security/ir.model.access.csv
odoo/addons/excel_import_export/static/description/common_wizard.png
odoo/addons/excel_import_export/static/description/icon.png
odoo/addons/excel_import_export/static/description/index.html
odoo/addons/excel_import_export/static/description/xlsx_template.png
odoo/addons/excel_import_export/static/src/js/report/action_manager_report.esm.js
odoo/addons/excel_import_export/views/xlsx_report.xml
odoo/addons/excel_import_export/views/xlsx_template_view.xml
odoo/addons/excel_import_export/wizard/__init__.py
odoo/addons/excel_import_export/wizard/export_xlsx_wizard.py
odoo/addons/excel_import_export/wizard/export_xlsx_wizard.xml
odoo/addons/excel_import_export/wizard/import_xlsx_wizard.py
odoo/addons/excel_import_export/wizard/import_xlsx_wizard.xml
odoo_addon_excel_import_export-18.0.1.0.0.3.dist-info/METADATA
odoo_addon_excel_import_export-18.0.1.0.0.3.dist-info/WHEEL
odoo_addon_excel_import_export-18.0.1.0.0.3.dist-info/top_level.txt
odoo_addon_excel_import_export-18.0.1.0.0.3.dist-info/RECORD
